{
  "id": "bc-template-ceilometer",
  "description": "Installation for Ceilometer",
  "attributes": {
    "ceilometer": {
      "debug": false,
      "verbose": true,
      "use_mongodb": true,
      "cpu_interval": 600,
      "meters_interval": 600,
      "metering_secret": "",
      "rabbitmq_instance": "none",
      "database_instance": "none",
      "keystone_instance": "none",
      "keystone_service_user": "ceilometer",
      "keystone_service_password": "",
      "gitrepo": "http://github.com/openstack/ceilometer.git",
      "git_instance": "",
      "git_refspec": "stable/havana",
      "use_gitrepo": false,
      "use_gitbarclamp": true,
      "use_pip_cache": true,
      "use_virtualenv": true,
      "pfs_deps": [
        "gawk",
        "sqlite3",
        "sudo"
      ],
      "api": {
        "protocol": "http",
        "port": 8777
      },
      "db": {
        "password": "",
        "user": "ceilometer",
        "database": "ceilometer"
      }
    }
  },
  "deployment": {
    "ceilometer": {
      "crowbar-revision": 0,
      "schema-revision": 4,
      "element_states": {
        "ceilometer-server": [ "readying", "ready", "applying" ],
        "ceilometer-cagent": [ "readying", "ready", "applying" ],
        "ceilometer-agent": [ "readying", "ready", "applying" ],
        "ceilometer-swift-proxy-middleware": [ "readying", "ready", "applying" ]
      },
      "elements": {},
      "element_order": [
        [ "ceilometer-server" ],
        [ "ceilometer-cagent" ], 
        [ "ceilometer-agent" ],
        [ "ceilometer-swift-proxy-middleware" ]
      ],
      "element_run_list_order": {
        "ceilometer-server": 101,
        "ceilometer-cagent": 102,
        "ceilometer-agent": 103,
        "ceilometer-swift-proxy-middleware" : 80
      },
      "config": {
        "environment": "ceilometer-base-config",
        "mode": "full",
        "transitions": false,
        "transition_list": [
        ]
      }
    }
  }
}

